Lab1/mux.v
`define AND and #20
`define OR or #20
`define NOT not #10

module mux8
(
    output out,
    input[7:0] ins,
    input[2:0] sel
);

    wire[7:0] selpick;	// One of these is true, corresponding to the input to forward to out
    wire ns0, ns1, ns2;
    wire s0s1, s0ns1, ns0s1, ns0ns1;    
    wire out0, out1, out2, out3, out4, out5, out6, out7;
    wire o0o1, o2o3, o4o5, o6o7, o0o1o2o3, o4o5o6o7;

    `NOT invert_sel_0 (ns0, sel[0]);   // Invert select bits for logic
    `NOT invert_sel_1 (ns1, sel[1]);
    `NOT invert_sel_2 (ns2, sel[2]);

    `AND and0 (s0s1, sel[0], sel[1]);  // Combinations of first two select bits
    `AND and1 (s0ns1, sel[0], ns1);
    `AND and2 (ns0s1, ns0, sel[1]);
    `AND and3 (ns0ns1, ns0, ns1);

    `AND and4 (selpick[0], ns0ns1, ns2);   // Determine which input to forward to out.
    `AND and5 (selpick[1], s0ns1, ns2);    // These cases should be exclusive and exhaustive.
    `AND and6 (selpick[2], ns0s1, ns2);
    `AND and7 (selpick[3], s0s1, ns2);
    `AND and8 (selpick[4], ns0ns1, sel[2]);
    `AND and9 (selpick[5], s0ns1, sel[2]);
    `AND and10 (selpick[6], ns0s1, sel[2]);
    `AND and11 (selpick[7], s0s1, sel[2]);

    `AND and12 (out0, selpick[0], ins[0]);   // If any of these "out" values are true,
    `AND and13 (out1, selpick[1], ins[1]);   // a condition has been met for a true output.
    `AND and14 (out2, selpick[2], ins[2]);
    `AND and15 (out3, selpick[3], ins[3]);
    `AND and16 (out4, selpick[4], ins[4]);
    `AND and17 (out5, selpick[5], ins[5]);
    `AND and18 (out6, selpick[6], ins[6]);
    `AND and19 (out7, selpick[7], ins[7]);

    `OR or0 (o0o1, out0, out1);   // Determine output by OR-ing them together.
    `OR or1 (o2o3, out2, out3);
    `OR or2 (o4o5, out4, out5);
    `OR or3 (o6o7, out6, out7);
    `OR or4 (o0o1o2o3, o0o1, o2o3);
    `OR or5 (o4o5o6o7, o4o5, o6o7);
    `OR output_gate (out, o0o1o2o3, o4o5o6o7);

endmodule

Lab1/mux.t.v
// 8-input mux testbench
`timescale 1 ns / 1 ps
`include "mux.v"

module testFullAdder();
    reg[7:0] ins;
    reg[2:0] sel;
    wire out;
    integer i;    

    mux8 test_mux (out, ins, sel);

    initial begin
        $dumpfile("mux8.vcd");
        $dumpvars();
        $display("   INPUT | SEL | OUT");
        
        //integer error = 0;

        
        ins = 8'b0000100;
        sel = 3'b010;
        #1000;

        $display("%b | %b |   %b", ins, sel, out);
       

        ins = 8'b0000100;
        sel = 3'b011;
	#1000;
        $display("%b | %b |   %b", ins, sel, out);

        ins = 8'b11111111;
        sel = 3'b111;
	#1000;
        $display("%b | %b |   %b", ins, sel, out);

        ins = 8'b01111111;
        sel = 3'b111;
	#1000;
        $display("%b | %b |   %b", ins, sel, out);

        $finish();

    end
endmodule

Lab1/mux8.vcd
$date
	Wed Oct  3 14:35:59 2018
$end
$version
	Icarus Verilog
$end
$timescale
	1ps
$end
$scope module testFullAdder $end
$var wire 1 ! out $end
$var reg 8 " ins [7:0] $end
$var reg 3 # sel [2:0] $end
$scope module test_mux $end
$var wire 8 $ ins [7:0] $end
$var wire 1 % ns0 $end
$var wire 1 & ns0ns1 $end
$var wire 1 ' ns0s1 $end
$var wire 1 ( ns1 $end
$var wire 1 ) ns2 $end
$var wire 1 * o0o1 $end
$var wire 1 + o0o1o2o3 $end
$var wire 1 , o2o3 $end
$var wire 1 - o4o5 $end
$var wire 1 . o4o5o6o7 $end
$var wire 1 / o6o7 $end
$var wire 1 ! out $end
$var wire 1 0 out0 $end
$var wire 1 1 out1 $end
$var wire 1 2 out2 $end
$var wire 1 3 out3 $end
$var wire 1 4 out4 $end
$var wire 1 5 out5 $end
$var wire 1 6 out6 $end
$var wire 1 7 out7 $end
$var wire 1 8 s0ns1 $end
$var wire 1 9 s0s1 $end
$var wire 3 : sel [2:0] $end
$var wire 8 ; selpick [7:0] $end
$upscope $end
$upscope $end
$enddefinitions $end
#0
$dumpvars
bx ;
b10 :
x9
x8
x7
x6
x5
x4
x3
x2
x1
x0
x/
x.
x-
x,
x+
x*
x)
x(
x'
x&
x%
b100 $
b10 #
b100 "
x!
$end
#10000
1%
0(
1)
#20000
09
08
b0xxxx ;
00
01
03
04
05
06
07
#30000
1'
0&
#40000
b0x0x ;
0*
0-
0/
#50000
b100 ;
#60000
0.
#70000
12
#90000
1,
#110000
1+
#130000
1!
#1000000
b11 #
b11 :
#1010000
0%
#1020000
19
#1030000
0'
#1040000
b1100 ;
#1050000
b1000 ;
#1070000
02
#1090000
0,
#1110000
0+
#1130000
0!
#2000000
b111 #
b111 :
b11111111 "
b11111111 $
#2010000
0)
#2020000
b10001000 ;
13
#2030000
b10000000 ;
#2040000
17
1,
#2050000
03
#2060000
1/
1+
#2070000
0,
#2080000
1.
1!
#2090000
0+
#3000000
b1111111 "
b1111111 $
#3020000
07
#3040000
0/
#3060000
0.
#3080000
0!
