Lab3/instruction_decoder.v
module instruction_decoder (

    // 32-bit instruction
    input[31:0] inst,

    // Outputs that are just parts of the input
    output[4:0] rs,
    output[4:0] rt,
    output[4:0] rd,
    output[15:0] imm16,
    output[25:0] target_instr,

    // Outputs that require logic
    output reg regDst,
    output reg regWr,
    output reg memWr,
    output reg memToReg,
    output reg [2:0] ALUcntrl,
    output reg ALUsrc, 
    output reg jump,
    output reg branch

);
wire[5:0] op;
wire[4:0] shamt;
wire[5:0] funct;
assign op = inst[31:26];
assign shamt = inst[10:6];
assign funct = inst[5:0];

assign rs = inst[25:21];
assign rt = inst[20:16];
assign rd = inst[15:11];
assign imm16 = inst[15:0];
assign target_instr = inst[25:0];

always @(op)begin
// Branch signal logic
if((op==6'b000100) || (op==6'b000101))
    branch = 1'b1;
else 
    branch = 1'b0;

// Jump signal logic
if((op==6'b000010)||(op==6'b000011)||(op==6'b0 && funct==6'b001000))
    jump = 1'b0;
else
    jump = 1'b1;


// ALusrc signal logic, ALUsrc is true on I type instructions
if((op!=6'b0)&&(op!=6'b10)&&(op!=6'b11)&&(op<6'b10000 && op >6'b010100))
    ALUsrc = 1'b1;
else
    ALUsrc = 1'b0;

// memToReg is true if LW instruciton - op==100011
if(op==6'b100011)
    memToReg = 1'b1;
else
    memToReg = 1'b0;

// ALUcntrl signal
// ALucntrl == 0, which is add operation, for LW,SW,ADDI and ADD
if((op==6'b100011)||(op==6'b101011)||(op==6'b1000)||((op==6'b0)&&(funct==6'b100000)))
    ALUcntrl = 3'b0;
// ALUcntrl == 1, which is sub operation, for SUB
if((op==6'b0)&&(funct==6'b100010))
    ALUcntrl = 3'b1;
// ALUcntrl ==2, which is SLT
if((op==6'b0)&&(funct==6'b101010))
    ALUcntrl = 3'h2;
// ALUcntrl == 3, which is XOR, for XORI, BEQ and BNE
if((op==6'h4)||(op==6'h5)||(op==6'he))
    ALUcntrl = 3'h3;

// Regwr signal logic, true for LW, XORI, ADDI, ADD, SUB, and SLT
if((op==6'h23)||(op==6'h3)||(op==6'he)||(op==6'h8)||((op==6'h0)&&((funct==6'h20)||(funct==6'h22)||(funct==6'h2a))))
    regWr = 1'b1;
else
    regWr = 1'b0;


// Instruction is R type if op code is 0 or 16-20
if ((op == 6'b000000) || (op[5:2] == 6'b0100))
    regDst = 1'b1;
else
    regDst = 1'b0;

// Write to memory only on store commands
if (op == 8'b101011)
    memWr = 1'b1;
else
    memWr = 1'b0;
end

endmodule

Lab4/instruction_decoder.t.v
`include "instruction_decoder.v"

module instruction_decoder_test();
reg[31:0] inst;
wire[4:0] rs;
wire[4:0] rt;
wire[4:0] rd;
wire[15:0] imm16;
wire[25:0] target_instr; 
wire[2:0] ALUcntrl;
wire regDst, regWr, memWr, memToReg, ALUsrc, jump, branch;

instruction_decoder decody(inst,rs,rt,rd,imm16,target_instr,regDst,regWr,memWr,memToReg,ALUcntrl,ALUsrc,jump,branch);

// Test each command type
initial begin
$dumpfile("instruction_decoder.vcd");
$dumpvars();
assign inst=32'b10001110101010101111111111111111;//LW
#100
assign inst=32'b10101110101010101111111111111111;//SW
#100
assign inst=32'b00001011111111111111111111111111;//J
#100
assign inst=32'b00000010101010101010111111001000;//JR
#100
assign inst=32'b00001111111111111111111111111111;//JL
#100
assign inst=32'b00010010101010101111111111111111;//BEQ
#100
assign inst=32'b00010110101010101111111111111111;//BNE
#100
assign inst=32'b00111010101010101111111111111111;//XORI
#100
assign inst=32'b00100010101010101111111111111111;//ADDI
#100
assign inst=32'b00000010101010101010111111100010;//SUB
#100
assign inst=32'b00000010101010101010111111100000;//ADD
#100
assign inst=32'b00000010101010101010111111101010;//SLT
#100
$finish();
end

endmodule

Lab4/instruction_decoder.vcd
$date
	Sun Nov 11 23:45:13 2018
$end
$version
	Icarus Verilog
$end
$timescale
	1s
$end
$scope module instruction_decoder_test $end
$var wire 26 ! target_instr [25:0] $end
$var wire 5 " rt [4:0] $end
$var wire 5 # rs [4:0] $end
$var wire 1 $ regWr $end
$var wire 1 % regDst $end
$var wire 5 & rd [4:0] $end
$var wire 1 ' memWr $end
$var wire 1 ( memToReg $end
$var wire 1 ) jump $end
$var wire 16 * imm16 [15:0] $end
$var wire 1 + branch $end
$var wire 1 , ALUsrc $end
$var wire 3 - ALUcntrl [2:0] $end
$var reg 32 . inst [31:0] $end
$scope module decody $end
$var wire 32 / inst [31:0] $end
$var wire 26 0 target_instr [25:0] $end
$var wire 5 1 shamt [4:0] $end
$var wire 5 2 rt [4:0] $end
$var wire 5 3 rs [4:0] $end
$var wire 5 4 rd [4:0] $end
$var wire 6 5 op [5:0] $end
$var wire 16 6 imm16 [15:0] $end
$var wire 6 7 funct [5:0] $end
$var reg 3 8 ALUcntrl [2:0] $end
$var reg 1 , ALUsrc $end
$var reg 1 + branch $end
$var reg 1 ) jump $end
$var reg 1 ( memToReg $end
$var reg 1 ' memWr $end
$var reg 1 % regDst $end
$var reg 1 $ regWr $end
$upscope $end
$upscope $end
$enddefinitions $end
#0
$dumpvars
b0 8
b111111 7
b1111111111111111 6
b100011 5
b11111 4
b10101 3
b1010 2
b11111 1
b10101010101111111111111111 0
b10001110101010101111111111111111 /
b10001110101010101111111111111111 .
b0 -
1,
0+
b1111111111111111 *
1)
1(
0'
b11111 &
0%
1$
b10101 #
b1010 "
b10101010101111111111111111 !
$end
#100
1'
0$
0(
b101011 5
b10101110101010101111111111111111 .
b10101110101010101111111111111111 /
#200
0'
0,
0)
b10 5
b11111 #
b11111 3
b11111 "
b11111 2
b11111111111111111111111111 !
b11111111111111111111111111 0
b1011111111111111111111111111 .
b1011111111111111111111111111 /
#300
1%
b0 5
b1000 7
b10101 #
b10101 3
b1010 "
b1010 2
b10101 &
b10101 4
b1010111111001000 *
b1010111111001000 6
b10101010101010111111001000 !
b10101010101010111111001000 0
b10101010101010111111001000 .
b10101010101010111111001000 /
#400
0%
1$
b11 5
b111111 7
b11111 #
b11111 3
b11111 "
b11111 2
b11111 &
b11111 4
b1111111111111111 *
b1111111111111111 6
b11111111111111111111111111 !
b11111111111111111111111111 0
b1111111111111111111111111111 .
b1111111111111111111111111111 /
#500
0$
b11 -
b11 8
1,
1)
1+
b100 5
b10101 #
b10101 3
b1010 "
b1010 2
b10101010101111111111111111 !
b10101010101111111111111111 0
b10010101010101111111111111111 .
b10010101010101111111111111111 /
#600
b101 5
b10110101010101111111111111111 .
b10110101010101111111111111111 /
#700
1$
0+
b1110 5
b111010101010101111111111111111 .
b111010101010101111111111111111 /
#800
b0 -
b0 8
b1000 5
b100010101010101111111111111111 .
b100010101010101111111111111111 /
#900
1%
b1 -
b1 8
0,
b0 5
b100010 7
b10101 &
b10101 4
b1010111111100010 *
b1010111111100010 6
b10101010101010111111100010 !
b10101010101010111111100010 0
b10101010101010111111100010 .
b10101010101010111111100010 /
#1000
b0 -
b0 8
b100000 7
b1010111111100000 *
b1010111111100000 6
b10101010101010111111100000 !
b10101010101010111111100000 0
b10101010101010111111100000 .
b10101010101010111111100000 /
#1100
b10 -
b10 8
b101010 7
b1010111111101010 *
b1010111111101010 6
b10101010101010111111101010 !
b10101010101010111111101010 0
b10101010101010111111101010 .
b10101010101010111111101010 /
