Lab2/inputconditioner.v
//------------------------------------------------------------------------
// Input Conditioner
//    1) Synchronizes input to clock domain
//    2) Debounces input
//    3) Creates pulses at edge transitions
//------------------------------------------------------------------------

module inputconditioner
(
input 	    clk,            // Clock domain to synchronize input to
input	    noisysignal,    // (Potentially) noisy input signal
output reg  conditioned,    // Conditioned output signal
output reg  positiveedge,   // 1 clk pulse at rising edge of conditioned
output reg  negativeedge    // 1 clk pulse at falling edge of conditioned
);

    parameter counterwidth = 3; // Counter size, in bits, >= log2(waittime)
    parameter waittime = 3;     // Debounce delay, in clock cycles
    
    reg[counterwidth-1:0] counter = 0;
    reg synchronizer0 = 0;
    reg synchronizer1 = 0;

   
    always @(posedge clk ) begin
        if(conditioned == synchronizer1) begin
            counter <= 0;

            negativeedge <= 1'b0;
            positiveedge <= 1'b0; // set to low
        end
        else begin
            if( counter == waittime) begin
                counter <= 0;
                conditioned <= synchronizer1;

                negativeedge <= conditioned&~synchronizer1; // detects edges
                positiveedge <= ~conditioned&synchronizer1;
            end
            else begin
                counter <= counter+1;

                negativeedge <= 1'b0; // sets to low
                positiveedge <= 1'b0;
            end
        end
        synchronizer0 <= noisysignal;
        synchronizer1 <= synchronizer0;

    end

endmodule

Lab2/inputconditioner.t.v
`include "inputconditioner.v"
//------------------------------------------------------------------------
// Input Conditioner test bench
//------------------------------------------------------------------------

module testConditioner();

    reg clk;
    reg pin;
    wire conditioned;
    wire rising;
    wire falling;
    
    inputconditioner dut(.clk(clk),
    			 .noisysignal(pin),
			 .conditioned(conditioned),
			 .positiveedge(rising),
			 .negativeedge(falling));


    // Generate clock (50MHz)
    initial clk=0;
    always #10 clk=!clk;    // 50MHz Clock
   
    initial pin=0;
    always #127 pin=!pin;  // Input Noisy Signal

    initial begin
        $dumpfile("inputconditioner.vcd");
        $dumpvars();
        #2500             // Test Length 

        $finish();
    end 
endmodule

Lab2/inputconditioner.vcd
$date
	Wed Oct 10 13:36:34 2018
$end
$version
	Icarus Verilog
$end
$timescale
	1s
$end
$scope module testConditioner $end
$var wire 1 ! rising $end
$var wire 1 " falling $end
$var wire 1 # conditioned $end
$var reg 1 $ clk $end
$var reg 1 % pin $end
$scope module dut $end
$var wire 1 $ clk $end
$var wire 1 % noisysignal $end
$var reg 1 # conditioned $end
$var reg 3 & counter [2:0] $end
$var reg 1 " negativeedge $end
$var reg 1 ! positiveedge $end
$var reg 1 ' synchronizer0 $end
$var reg 1 ( synchronizer1 $end
$upscope $end
$upscope $end
$enddefinitions $end
#0
$dumpvars
0(
0'
b0 &
0%
0$
x#
x"
x!
$end
#10
0!
0"
b1 &
1$
#20
0$
#30
b10 &
1$
#40
0$
#50
b11 &
1$
#60
0$
#70
x"
0#
b0 &
1$
#80
0$
#90
0"
1$
#100
0$
#110
1$
#120
0$
#127
1%
#130
1'
1$
#140
0$
#150
1(
1$
#160
0$
#170
b1 &
1$
#180
0$
#190
b10 &
1$
#200
0$
#210
b11 &
1$
#220
0$
#230
1!
1#
b0 &
1$
#240
0$
#250
0!
1$
#254
0%
#260
0$
#270
0'
1$
#280
0$
#290
0(
1$
#300
0$
#310
b1 &
1$
#320
0$
#330
b10 &
1$
#340
0$
#350
b11 &
1$
#360
0$
#370
1"
0#
b0 &
1$
#380
0$
#381
1%
#390
1'
0"
1$
#400
0$
#410
1(
1$
#420
0$
#430
b1 &
1$
#440
0$
#450
b10 &
1$
#460
0$
#470
b11 &
1$
#480
0$
#490
1!
1#
b0 &
1$
#500
0$
#508
0%
#510
0'
0!
1$
#520
0$
#530
0(
1$
#540
0$
#550
b1 &
1$
#560
0$
#570
b10 &
1$
#580
0$
#590
b11 &
1$
#600
0$
#610
1"
0#
b0 &
1$
#620
0$
#630
0"
1$
#635
1%
#640
0$
#650
1'
1$
#660
0$
#670
1(
1$
#680
0$
#690
b1 &
1$
#700
0$
#710
b10 &
1$
#720
0$
#730
b11 &
1$
#740
0$
#750
1!
1#
b0 &
1$
#760
0$
#762
0%
#770
0'
0!
1$
#780
0$
#790
0(
1$
#800
0$
#810
b1 &
1$
#820
0$
#830
b10 &
1$
#840
0$
#850
b11 &
1$
#860
0$
#870
1"
0#
b0 &
1$
#880
0$
#889
1%
#890
1'
0"
1$
#900
0$
#910
1(
1$
#920
0$
#930
b1 &
1$
#940
0$
#950
b10 &
1$
#960
0$
#970
b11 &
1$
#980
0$
#990
1!
1#
b0 &
1$
#1000
0$
#1010
0!
1$
#1016
0%
#1020
0$
#1030
0'
1$
#1040
0$
#1050
0(
1$
#1060
0$
#1070
b1 &
1$
#1080
0$
#1090
b10 &
1$
#1100
0$
#1110
b11 &
1$
#1120
0$
#1130
1"
0#
b0 &
1$
#1140
0$
#1143
1%
#1150
1'
0"
1$
#1160
0$
#1170
1(
1$
#1180
0$
#1190
b1 &
1$
#1200
0$
#1210
b10 &
1$
#1220
0$
#1230
b11 &
1$
#1240
0$
#1250
1!
1#
b0 &
1$
#1260
0$
#1270
0'
0!
1$
0%
#1280
0$
#1290
0(
1$
#1300
0$
#1310
b1 &
1$
#1320
0$
#1330
b10 &
1$
#1340
0$
#1350
b11 &
1$
#1360
0$
#1370
1"
0#
b0 &
1$
#1380
0$
#1390
0"
1$
#1397
1%
#1400
0$
#1410
1'
1$
#1420
0$
#1430
1(
1$
#1440
0$
#1450
b1 &
1$
#1460
0$
#1470
b10 &
1$
#1480
0$
#1490
b11 &
1$
#1500
0$
#1510
1!
1#
b0 &
1$
#1520
0$
#1524
0%
#1530
0'
0!
1$
#1540
0$
#1550
0(
1$
#1560
0$
#1570
b1 &
1$
#1580
0$
#1590
b10 &
1$
#1600
0$
#1610
b11 &
1$
#1620
0$
#1630
1"
0#
b0 &
1$
#1640
0$
#1650
0"
1$
#1651
1%
#1660
0$
#1670
1'
1$
#1680
0$
#1690
1(
1$
#1700
0$
#1710
b1 &
1$
#1720
0$
#1730
b10 &
1$
#1740
0$
#1750
b11 &
1$
#1760
0$
#1770
1!
1#
b0 &
1$
#1778
0%
#1780
0$
#1790
0'
0!
1$
#1800
0$
#1810
0(
1$
#1820
0$
#1830
b1 &
1$
#1840
0$
#1850
b10 &
1$
#1860
0$
#1870
b11 &
1$
#1880
0$
#1890
1"
0#
b0 &
1$
#1900
0$
#1905
1%
#1910
1'
0"
1$
#1920
0$
#1930
1(
1$
#1940
0$
#1950
b1 &
1$
#1960
0$
#1970
b10 &
1$
#1980
0$
#1990
b11 &
1$
#2000
0$
#2010
1!
1#
b0 &
1$
#2020
0$
#2030
0!
1$
#2032
0%
#2040
0$
#2050
0'
1$
#2060
0$
#2070
0(
1$
#2080
0$
#2090
b1 &
1$
#2100
0$
#2110
b10 &
1$
#2120
0$
#2130
b11 &
1$
#2140
0$
#2150
1"
0#
b0 &
1$
#2159
1%
#2160
0$
#2170
1'
0"
1$
#2180
0$
#2190
1(
1$
#2200
0$
#2210
b1 &
1$
#2220
0$
#2230
b10 &
1$
#2240
0$
#2250
b11 &
1$
#2260
0$
#2270
1!
1#
b0 &
1$
#2280
0$
#2286
0%
#2290
0'
0!
1$
#2300
0$
#2310
0(
1$
#2320
0$
#2330
b1 &
1$
#2340
0$
#2350
b10 &
1$
#2360
0$
#2370
b11 &
1$
#2380
0$
#2390
1"
0#
b0 &
1$
#2400
0$
#2410
0"
1$
#2413
1%
#2420
0$
#2430
1'
1$
#2440
0$
#2450
1(
1$
#2460
0$
#2470
b1 &
1$
#2480
0$
#2490
b10 &
1$
